pygsearch/__init__.py
pygsearch/gsearch.py
pygsearch-0.6.0.dist-info/LICENSE
pygsearch-0.6.0.dist-info/METADATA
pygsearch-0.6.0.dist-info/WHEEL
pygsearch-0.6.0.dist-info/RECORD
