Metadata-Version: 2.3
Name: pygsearch
Version: 0.6.0
Summary: Python library to get google search results
License: MIT
Keywords: search,google,query,python
Author: atbuy
Author-email: buy@atbuy.dev
Requires-Python: >=3.9,<4.0
Classifier: Development Status :: 3 - Alpha
Classifier: Intended Audience :: Developers
Classifier: Intended Audience :: Information Technology
Classifier: License :: OSI Approved :: MIT License
Classifier: Natural Language :: English
Classifier: Operating System :: OS Independent
Classifier: Programming Language :: Python
Classifier: Programming Language :: Python :: 3
Classifier: Programming Language :: Python :: 3.9
Classifier: Programming Language :: Python :: 3.10
Classifier: Programming Language :: Python :: 3.11
Classifier: Programming Language :: Python :: 3.12
Classifier: Programming Language :: Python :: 3.13
Classifier: Topic :: Software Development :: Libraries
Classifier: Topic :: Software Development :: Libraries :: Python Modules
Classifier: Topic :: Utilities
Requires-Dist: beautifulsoup4 (>=4,<5)
Requires-Dist: lxml (>=5,<6)
Requires-Dist: requests (>=2.32.3,<3.0.0)
Project-URL: Bug Tracker, https://github.com/atbuy/pygsearch/issues
Project-URL: CI/CD, https://github.com/atbuy/pygsearch/actions
Project-URL: Homepage, https://github.com/atbuy/pygsearch
Project-URL: Repository, https://github.com/atbuy/pygsearch
Project-URL: Source Code, https://github.com/atbuy/pygsearch
